LICENSE
MANIFEST.in
README.md
pyproject.toml
setup.py
DTLSSocket/DTLSSocket.py
DTLSSocket/__init__.py
DTLSSocket/dtls.pyx
DTLSSocket/tdtls.pxd
DTLSSocket.egg-info/PKG-INFO
DTLSSocket.egg-info/SOURCES.txt
DTLSSocket.egg-info/dependency_links.txt
DTLSSocket.egg-info/top_level.txt
DTLSSocket/tinydtls/ABOUT.md
DTLSSocket/tinydtls/CONTRIBUTING.md
DTLSSocket/tinydtls/LICENSE
DTLSSocket/tinydtls/Makefile.in
DTLSSocket/tinydtls/alert.h
DTLSSocket/tinydtls/autogen.sh
DTLSSocket/tinydtls/ccm.c
DTLSSocket/tinydtls/ccm.h
DTLSSocket/tinydtls/configure.ac
DTLSSocket/tinydtls/crypto.c
DTLSSocket/tinydtls/crypto.h
DTLSSocket/tinydtls/dtls.c
DTLSSocket/tinydtls/dtls.h
DTLSSocket/tinydtls/dtls_config.h
DTLSSocket/tinydtls/dtls_debug.c
DTLSSocket/tinydtls/dtls_debug.h
DTLSSocket/tinydtls/dtls_mutex.h
DTLSSocket/tinydtls/dtls_prng.h
DTLSSocket/tinydtls/dtls_time.c
DTLSSocket/tinydtls/dtls_time.h
DTLSSocket/tinydtls/global.h
DTLSSocket/tinydtls/hmac.c
DTLSSocket/tinydtls/hmac.h
DTLSSocket/tinydtls/netq.c
DTLSSocket/tinydtls/netq.h
DTLSSocket/tinydtls/numeric.h
DTLSSocket/tinydtls/peer.c
DTLSSocket/tinydtls/peer.h
DTLSSocket/tinydtls/session.c
DTLSSocket/tinydtls/session.h
DTLSSocket/tinydtls/state.h
DTLSSocket/tinydtls/tinydtls.h
DTLSSocket/tinydtls/uthash.h
DTLSSocket/tinydtls/utlist.h
DTLSSocket/tinydtls/aes/Makefile.in
DTLSSocket/tinydtls/aes/rijndael.c
DTLSSocket/tinydtls/aes/rijndael.h
DTLSSocket/tinydtls/aes/rijndael_wrap.c
DTLSSocket/tinydtls/doc/Doxyfile.in
DTLSSocket/tinydtls/doc/Makefile.in
DTLSSocket/tinydtls/ecc/Makefile.in
DTLSSocket/tinydtls/ecc/ecc.c
DTLSSocket/tinydtls/ecc/ecc.h
DTLSSocket/tinydtls/ecc/test_helper.h
DTLSSocket/tinydtls/platform-specific/Makefile.in
DTLSSocket/tinydtls/platform-specific/dtls_prng_posix.c
DTLSSocket/tinydtls/platform-specific/lwip_platform.h
DTLSSocket/tinydtls/platform-specific/platform.h
DTLSSocket/tinydtls/platform-specific/riot_boards.h
DTLSSocket/tinydtls/sha2/Makefile.in
DTLSSocket/tinydtls/sha2/README
DTLSSocket/tinydtls/sha2/sha2.c
DTLSSocket/tinydtls/sha2/sha2.h
DTLSSocket/tinydtls/tests/Makefile.in
DTLSSocket/tinydtls/tests/dtls_ciphers_util.h
