Metadata-Version: 2.1
Name: DTLSSocket
Version: 0.2.1
Summary: DTLSSocket is a cython wrapper for tinydtls with a Socket like interface
Home-page: https://git.fslab.de/jkonra2m/tinydtls-cython
Author: Jannis Konrad
Author-email: Kabel42@gmail.com
Classifier: License :: OSI Approved :: Eclipse Public License 1.0 (EPL-1.0)
License-File: LICENSE
